UnionFindPy/__init__.py
UnionFindPy/_union_find_py.cpython-38-darwin.so
UnionFindPy/_version.py
UnionFindPy/decoder.py
UnionFindPy/cpp/CMakeLists.txt
UnionFindPy/cpp/Makefile
tests/__init__.py
tests/test_decoder.py
UnionFindPy-0.2.1.dist-info/LICENSE
UnionFindPy-0.2.1.dist-info/METADATA
UnionFindPy-0.2.1.dist-info/WHEEL
UnionFindPy-0.2.1.dist-info/top_level.txt
UnionFindPy-0.2.1.dist-info/RECORD
