Metadata-Version: 2.1
Name: UnionFindPy
Version: 0.2.1
Summary: C++ implemenation of UnionFind with a python binding
Home-page: https://github.com/chaeyeunpark/UnionFind
Maintainer: Chae-Yeun Park
Maintainer-email: chae.yeun.park@gmail.com
License: GNU Lesser General Public License v2.1
Platform: UNKNOWN
Classifier: Development Status :: 2 - Pre-Alpha
Classifier: Environment :: Console
Classifier: Intended Audience :: Science/Research
Classifier: License :: OSI Approved :: GNU Lesser General Public License v2 or later (LGPLv2+)
Classifier: Natural Language :: English
Classifier: Operating System :: POSIX
Classifier: Operating System :: MacOS :: MacOS X
Classifier: Operating System :: POSIX :: Linux
Classifier: Operating System :: Microsoft :: Windows
Classifier: Programming Language :: Python
Classifier: Programming Language :: Python :: 3
Classifier: Programming Language :: Python :: 3.7
Classifier: Programming Language :: Python :: 3.8
Classifier: Programming Language :: Python :: 3.9
Classifier: Programming Language :: Python :: 3 :: Only
Classifier: Topic :: Scientific/Engineering :: Physics
Provides: UnionFindPy
License-File: LICENSE
Requires-Dist: ninja
